[
  {
    "set": "Holon Phantoms 1/111",
    "cost": "Not PSA Graded: $13.9",
    "img": "https://images.pokemontcg.io/ex13/1.png"
  },
  {
    "set": "Sandstorm 1/100",
    "cost": "Not PSA Graded: $14.44",
    "img": "https://images.pokemontcg.io/ex2/1.png"
  },
  {
    "set": "Power Keepers 3/108",
    "cost": "Not PSA Graded: $7.07",
    "img": "https://images.pokemontcg.io/ex16/3.png"
  },
  {
    "set": "POP Series 1 16/17",
    "cost": "Not PSA Graded: $21.76",
    "img": "https://images.pokemontcg.io/pop1/16.png"
  },
  {
    "set": "Legends Awakened 18/146",
    "cost": "Not PSA Graded: $1.79",
    "img": "https://images.pokemontcg.io/dp6/18.png"
  },
  {
    "set": "Steam Siege 57/116",
    "cost": "Not PSA Graded: $0.32",
    "img": "https://images.pokemontcg.io/xy11/57.png"
  },
  {
    "set": "Legend Maker 84/93",
    "cost": "Not PSA Graded: $102.42",
    "img": "https://images.pokemontcg.io/ex12/84.png"
  },
  {
    "set": "Cosmic Eclipse 112/272",
    "cost": "Not PSA Graded: $0.29",
    "img": "https://images.pokemontcg.io/sm12/112.png"
  },
  {
    "set": "Silver Tempest 96/215",
    "cost": "Not PSA Graded: $0.14",
    "img": "https://images.pokemontcg.io/swsh12/96.png"
  }
]