[
  {
    "set": "DP Black Star Promos DP06/56",
    "cost": "Not PSA Graded: $4.16",
    "img": "https://images.pokemontcg.io/dpp/DP06.png"
  },
  {
    "set": "POP Series 9 12/17",
    "cost": "Not PSA Graded: $0.61",
    "img": "https://images.pokemontcg.io/pop9/12.png"
  },
  {
    "set": "POP Series 6 12/17",
    "cost": "Not PSA Graded: $2.6",
    "img": "https://images.pokemontcg.io/pop6/12.png"
  },
  {
    "set": "Arceus 55/111",
    "cost": "Not PSA Graded: $0.33",
    "img": "https://images.pokemontcg.io/pl4/55.png"
  },
  {
    "set": "Majestic Dawn 53/100",
    "cost": "Not PSA Graded: $0.43",
    "img": "https://images.pokemontcg.io/dp5/53.png"
  },
  {
    "set": "Diamond & Pearl 73/130",
    "cost": "Not PSA Graded: $0.35",
    "img": "https://images.pokemontcg.io/dp1/73.png"
  },
  {
    "set": "Flashfire 84/110",
    "cost": "Not PSA Graded: $0.29",
    "img": "https://images.pokemontcg.io/xy2/84.png"
  },
  {
    "set": "Legends Awakened 86/146",
    "cost": "Not PSA Graded: $0.35",
    "img": "https://images.pokemontcg.io/dp6/86.png"
  },
  {
    "set": "Supreme Victors 94/153",
    "cost": "Not PSA Graded: $0.41",
    "img": "https://images.pokemontcg.io/pl3/94.png"
  },
  {
    "set": "Ultra Prism 106/178",
    "cost": "Not PSA Graded: $0.17",
    "img": "https://images.pokemontcg.io/sm5/106.png"
  },
  {
    "set": "Boundaries Crossed 116/153",
    "cost": "Not PSA Graded: $0.38",
    "img": "https://images.pokemontcg.io/bw7/116.png"
  },
  {
    "set": "Fusion Strike 212/284",
    "cost": "Not PSA Graded: $0.06",
    "img": "https://images.pokemontcg.io/swsh8/212.png"
  },
  {
    "set": "Silver Tempest 144/215",
    "cost": "Not PSA Graded: $0.1",
    "img": "https://images.pokemontcg.io/swsh12/144.png"
  },
  {
    "set": "Prismatic Evolutions 83/180",
    "cost": "Not PSA Graded: $0.08",
    "img": "https://images.pokemontcg.io/sv8pt5/83.png"
  },
  {
    "set": "Mega Evolution 107/188",
    "cost": "Not PSA Graded: $0.08",
    "img": "https://images.pokemontcg.io/me1/107.png"
  },
  {
    "set": "Phantasmal Flames 83/130",
    "cost": "Not PSA Graded: $0.12",
    "img": "https://images.pokemontcg.io/me2/83.png"
  }
]