[
  {
    "set": "Pokémon Rumble 2/16",
    "cost": "Not PSA Graded: $45.05",
    "img": "https://images.pokemontcg.io/ru1/2.png"
  },
  {
    "set": "Plasma Storm 7/138",
    "cost": "Not PSA Graded: $1.26",
    "img": "https://images.pokemontcg.io/bw8/7.png"
  },
  {
    "set": "Ultra Prism 11/178",
    "cost": "Not PSA Graded: $0.31",
    "img": "https://images.pokemontcg.io/sm5/11.png"
  },
  {
    "set": "POP Series 8 6/17",
    "cost": "Not PSA Graded: $2.48",
    "img": "https://images.pokemontcg.io/pop8/6.png"
  },
  {
    "set": "Arceus 15/111",
    "cost": "Not PSA Graded: $4.36",
    "img": "https://images.pokemontcg.io/pl4/15.png"
  },
  {
    "set": "Stormfront 14/106",
    "cost": "Not PSA Graded: $1.2",
    "img": "https://images.pokemontcg.io/dp7/14.png"
  },
  {
    "set": "HS—Unleashed 28/96",
    "cost": "Not PSA Graded: $0.56",
    "img": "https://images.pokemontcg.io/hgss2/28.png"
  },
  {
    "set": "Diamond & Pearl 45/130",
    "cost": "Not PSA Graded: $0.66",
    "img": "https://images.pokemontcg.io/dp1/45.png"
  },
  {
    "set": "Supreme Victors 55/153",
    "cost": "Not PSA Graded: $1.27",
    "img": "https://images.pokemontcg.io/pl3/55.png"
  },
  {
    "set": "Battle Styles 8/183",
    "cost": "Not PSA Graded: $0.66",
    "img": "https://images.pokemontcg.io/swsh5/8.png"
  },
  {
    "set": "SWSH Black Star Promos SWSH088/304",
    "cost": "Not PSA Graded: $8.08",
    "img": "https://images.pokemontcg.io/swshp/SWSH088.png"
  }
]