[
  {
    "set": "Forbidden Light 26/150",
    "cost": "Not PSA Graded: $0.32",
    "img": "https://images.pokemontcg.io/sm6/26.png"
  },
  {
    "set": "Steam Siege 34/116",
    "cost": "Not PSA Graded: $0.28",
    "img": "https://images.pokemontcg.io/xy11/34.png"
  },
  {
    "set": "Steam Siege 35/116",
    "cost": "Not PSA Graded: $2.52",
    "img": "https://images.pokemontcg.io/xy11/35.png"
  },
  {
    "set": "Furious Fists 24/114",
    "cost": "Not PSA Graded: $0.66",
    "img": "https://images.pokemontcg.io/xy3/24.png"
  },
  {
    "set": "XY Black Star Promos XY146/216",
    "cost": "Not PSA Graded: $7.22",
    "img": "https://images.pokemontcg.io/xyp/XY146.png"
  },
  {
    "set": "Fusion Strike 75/284",
    "cost": "Not PSA Graded: $0.09",
    "img": "https://images.pokemontcg.io/swsh8/75.png"
  },
  {
    "set": "Scarlet & Violet 50/258",
    "cost": "Not PSA Graded: $0.05",
    "img": "https://images.pokemontcg.io/sv1/50.png"
  },
  {
    "set": "Mega Evolution 38/188",
    "cost": "Not PSA Graded: $0.05",
    "img": "https://images.pokemontcg.io/me1/38.png"
  },
  {
    "set": "Mega Evolution 141/188",
    "cost": "Not PSA Graded: $1.19",
    "img": "https://images.pokemontcg.io/me1/141.png"
  }
]