[
  {
    "code": "009/202",
    "set": "Sword & Shield 009/202",
    "cost": "UnGraded: $0.82",
    "img": "https://images.pokemontcg.io/swsh1/9.png"
  },
  {
    "code": "019/185",
    "set": "Vivid Voltage 019/185",
    "cost": "UnGraded: $0.04",
    "img": "https://images.pokemontcg.io/swsh4/19.png"
  },
  {
    "code": "022/168",
    "set": "Celestial Storm 022/168",
    "cost": "UnGraded: $0.25",
    "img": "https://images.pokemontcg.io/sm7/22.png"
  },
  {
    "code": "020/236",
    "set": "Unified Minds 020/236",
    "cost": "UnGraded: $0.13",
    "img": "https://images.pokemontcg.io/sm11/20.png"
  },
  {
    "code": "SM53/248",
    "set": "SM Black Star Promos SM53/248",
    "cost": "UnGraded: $0.82",
    "img": "https://images.pokemontcg.io/smp/SM53.png"
  },
  {
    "code": "059/145",
    "set": "Guardians Rising 059/145",
    "cost": "UnGraded: $0.31",
    "img": "https://images.pokemontcg.io/sm2/59.png"
  },
  {
    "code": "098/236",
    "set": "Cosmic Eclipse 098/236",
    "cost": "UnGraded: $0.17",
    "img": "https://images.pokemontcg.io/sm12/98.png"
  },
  {
    "code": "187/202",
    "set": "Sword & Shield 187/202",
    "cost": "UnGraded: $2.81",
    "img": "https://images.pokemontcg.io/swsh1/187.png"
  },
  {
    "code": "009/72",
    "set": "Shining Fates 009/72",
    "cost": "UnGraded: $0.69",
    "img": "https://images.pokemontcg.io/swsh45/9.png"
  },
  {
    "code": "010/72",
    "set": "Shining Fates 010/72",
    "cost": "UnGraded: $1.44",
    "img": "https://images.pokemontcg.io/swsh45/10.png"
  },
  {
    "code": "019/162",
    "set": "Temporal Forces 019/162",
    "cost": "UnGraded: $0.04",
    "img": "https://images.pokemontcg.io/sv5/19.png"
  },
  {
    "code": "010/191",
    "set": "Surging Sparks 010/191",
    "cost": "UnGraded: $0.05",
    "img": "https://images.pokemontcg.io/sv8/10.png"
  },
  {
    "code": "070/159",
    "set": "Journey Together 070/159",
    "cost": "UnGraded: $0.05",
    "img": "https://images.pokemontcg.io/sv9/70.png"
  },
  {
    "code": "018/132",
    "set": "Mega Evolution 018/132",
    "cost": "UnGraded: $0.03",
    "img": "https://images.pokemontcg.io/me1/18.png"
  }
]