[
  {
    "set": "Diamond & Pearl 1/130",
    "cost": "Not PSA Graded: $29.16",
    "img": "https://images.pokemontcg.io/dp1/1.png"
  },
  {
    "set": "Call of Legends 3/106",
    "cost": "Not PSA Graded: $9.68",
    "img": "https://images.pokemontcg.io/col1/3.png"
  },
  {
    "set": "Platinum 5/133",
    "cost": "Not PSA Graded: $10.44",
    "img": "https://images.pokemontcg.io/pl1/5.png"
  },
  {
    "set": "Platinum 6/133",
    "cost": "Not PSA Graded: $10.08",
    "img": "https://images.pokemontcg.io/pl1/6.png"
  },
  {
    "set": "Platinum 7/133",
    "cost": "Not PSA Graded: $11.7",
    "img": "https://images.pokemontcg.io/pl1/7.png"
  },
  {
    "set": "Majestic Dawn 4/100",
    "cost": "Not PSA Graded: $35.56",
    "img": "https://images.pokemontcg.io/dp5/4.png"
  },
  {
    "set": "DP Black Star Promos DP17/56",
    "cost": "Not PSA Graded: $43.39",
    "img": "https://images.pokemontcg.io/dpp/DP17.png"
  },
  {
    "set": "Great Encounters 16/106",
    "cost": "Not PSA Graded: $1.74",
    "img": "https://images.pokemontcg.io/dp4/16.png"
  },
  {
    "set": "Platinum 23/133",
    "cost": "Not PSA Graded: $1.85",
    "img": "https://images.pokemontcg.io/pl1/23.png"
  },
  {
    "set": "DP Black Star Promos DP26/56",
    "cost": "Not PSA Graded: $7.57",
    "img": "https://images.pokemontcg.io/dpp/DP26.png"
  },
  {
    "set": "DP Black Star Promos DP37/56",
    "cost": "Not PSA Graded: $31.52",
    "img": "https://images.pokemontcg.io/dpp/DP37.png"
  },
  {
    "set": "DP Black Star Promos DP49/56",
    "cost": "Not PSA Graded: $8.78",
    "img": "https://images.pokemontcg.io/dpp/DP49.png"
  },
  {
    "set": "Plasma Blast 65/105",
    "cost": "Not PSA Graded: $24.13",
    "img": "https://images.pokemontcg.io/bw10/65.png"
  },
  {
    "set": "Phantom Forces 62/124",
    "cost": "Not PSA Graded: $10.99",
    "img": "https://images.pokemontcg.io/xy4/62.png"
  },
  {
    "set": "XY Black Star Promos XY77/216",
    "cost": "Not PSA Graded: $37.78",
    "img": "https://images.pokemontcg.io/xyp/XY77.png"
  },
  {
    "set": "Forbidden Light 82/150",
    "cost": "Not PSA Graded: $6.36",
    "img": "https://images.pokemontcg.io/sm6/82.png"
  },
  {
    "set": "Plasma Blast 99/105",
    "cost": "Not PSA Graded: $350",
    "img": "https://images.pokemontcg.io/bw10/99.png"
  },
  {
    "set": "Call of Legends SL2/106",
    "cost": null,
    "img": "https://images.pokemontcg.io/col1/SL2.png"
  },
  {
    "set": "Ultra Prism 100/178",
    "cost": "Not PSA Graded: $7.17",
    "img": "https://images.pokemontcg.io/sm5/100.png"
  },
  {
    "set": "HS—Triumphant 101/103",
    "cost": "Not PSA Graded: $137.5",
    "img": "https://images.pokemontcg.io/hgss4/101.png"
  },
  {
    "set": "HS—Triumphant 102/103",
    "cost": "Not PSA Graded: $88.61",
    "img": "https://images.pokemontcg.io/hgss4/102.png"
  },
  {
    "set": "Great Encounters 105/106",
    "cost": "Not PSA Graded: $129.99",
    "img": "https://images.pokemontcg.io/dp4/105.png"
  },
  {
    "set": "Platinum 122/133",
    "cost": "Not PSA Graded: $43.84",
    "img": "https://images.pokemontcg.io/pl1/122.png"
  },
  {
    "set": "Vivid Voltage 121/203",
    "cost": "Not PSA Graded: $0.3",
    "img": "https://images.pokemontcg.io/swsh4/121.png"
  },
  {
    "set": "Phantom Forces 122/124",
    "cost": "Not PSA Graded: $1083.33",
    "img": "https://images.pokemontcg.io/xy4/122.png"
  },
  {
    "set": "Lost Thunder 127/240",
    "cost": "Not PSA Graded: $1.2",
    "img": "https://images.pokemontcg.io/sm8/127.png"
  },
  {
    "set": "Forbidden Light 125/150",
    "cost": "Not PSA Graded: $34.19",
    "img": "https://images.pokemontcg.io/sm6/125.png"
  },
  {
    "set": "Ultra Prism 146/178",
    "cost": "Not PSA Graded: $18.29",
    "img": "https://images.pokemontcg.io/sm5/146.png"
  },
  {
    "set": "Forbidden Light 138/150",
    "cost": "Not PSA Graded: $72.94",
    "img": "https://images.pokemontcg.io/sm6/138.png"
  },
  {
    "set": "Cosmic Eclipse 156/272",
    "cost": "Not PSA Graded: $25.98",
    "img": "https://images.pokemontcg.io/sm12/156.png"
  },
  {
    "set": "Ultra Prism 164/178",
    "cost": "Not PSA Graded: $40.32",
    "img": "https://images.pokemontcg.io/sm5/164.png"
  },
  {
    "set": "Cosmic Eclipse 220/272",
    "cost": "Not PSA Graded: $56.26",
    "img": "https://images.pokemontcg.io/sm12/220.png"
  },
  {
    "set": "Cosmic Eclipse 221/272",
    "cost": "Not PSA Graded: $452.79",
    "img": "https://images.pokemontcg.io/sm12/221.png"
  },
  {
    "set": "Cosmic Eclipse 258/272",
    "cost": "Not PSA Graded: $72.25",
    "img": "https://images.pokemontcg.io/sm12/258.png"
  },
  {
    "set": "Evolving Skies 112/237",
    "cost": "Not PSA Graded: $0.22",
    "img": "https://images.pokemontcg.io/swsh7/112.png"
  },
  {
    "set": "Celebrations 20/25",
    "cost": "Not PSA Graded: $0.22",
    "img": "https://images.pokemontcg.io/cel25/20.png"
  },
  {
    "set": "Astral Radiance 113/216",
    "cost": "Not PSA Graded: $1.13",
    "img": "https://images.pokemontcg.io/swsh10/113.png"
  },
  {
    "set": "Astral Radiance 114/216",
    "cost": "Not PSA Graded: $1.26",
    "img": "https://images.pokemontcg.io/swsh10/114.png"
  },
  {
    "set": "Astral Radiance 177/216",
    "cost": "Not PSA Graded: $54.43",
    "img": "https://images.pokemontcg.io/swsh10/177.png"
  },
  {
    "set": "Astral Radiance 198/216",
    "cost": "Not PSA Graded: $13.17",
    "img": "https://images.pokemontcg.io/swsh10/198.png"
  },
  {
    "set": "Astral Radiance 210/216",
    "cost": "Not PSA Graded: $10.26",
    "img": "https://images.pokemontcg.io/swsh10/210.png"
  },
  {
    "set": "SWSH Black Star Promos SWSH255/304",
    "cost": "Not PSA Graded: $2.59",
    "img": "https://images.pokemontcg.io/swshp/SWSH255.png"
  },
  {
    "set": "SWSH Black Star Promos SWSH256/304",
    "cost": "Not PSA Graded: $1.82",
    "img": "https://images.pokemontcg.io/swshp/SWSH256.png"
  },
  {
    "set": "Crown Zenith Galarian Gallery GG68/70",
    "cost": "Not PSA Graded: $85.62",
    "img": "https://images.pokemontcg.io/swsh12pt5gg/GG68.png"
  },
  {
    "set": "Surging Sparks 135/252",
    "cost": "Not PSA Graded: $0.12",
    "img": "https://images.pokemontcg.io/sv8/135.png"
  },
  {
    "set": "Scarlet & Violet Promos 180/148",
    "cost": "Not PSA Graded: $0.99",
    "img": "https://images.pokemontcg.io/svp/180.png"
  },
  {
    "set": "Mega Evolution 95/188",
    "cost": "Not PSA Graded: $0.07",
    "img": "https://images.pokemontcg.io/me1/95.png"
  }
]