[
  {
    "code": "XY02/211",
    "set": "XY Black Star Promos XY02/211",
    "cost": "UnGraded: $4.02",
    "img": "https://images.pokemontcg.io/xyp/XY02.png"
  },
  {
    "code": "010/124",
    "set": "Fates Collide 010/124",
    "cost": "UnGraded: $0.16",
    "img": "https://images.pokemontcg.io/xy10/10.png"
  },
  {
    "code": "011/124",
    "set": "Fates Collide 011/124",
    "cost": "UnGraded: $0.17",
    "img": "https://images.pokemontcg.io/xy10/11.png"
  },
  {
    "code": "003/12",
    "set": "McDonald's Collection 2016 003/12",
    "cost": null,
    "img": "https://images.pokemontcg.io/mcd16/3.png"
  },
  {
    "code": "008/39",
    "set": "Kalos Starter Set 008/39",
    "cost": "UnGraded: $1.94",
    "img": "https://images.pokemontcg.io/xy0/8.png"
  },
  {
    "code": "014/131",
    "set": "Forbidden Light 014/131",
    "cost": "UnGraded: $0.21",
    "img": "https://images.pokemontcg.io/sm6/14.png"
  },
  {
    "code": "015/131",
    "set": "Forbidden Light 015/131",
    "cost": "UnGraded: $0.17",
    "img": "https://images.pokemontcg.io/sm6/15.png"
  },
  {
    "code": "024/146",
    "set": "XY 024/146",
    "cost": "UnGraded: $0.3",
    "img": "https://images.pokemontcg.io/xy1/24.png"
  },
  {
    "code": "025/162",
    "set": "BREAKthrough 025/162",
    "cost": "UnGraded: $0.16",
    "img": "https://images.pokemontcg.io/xy8/25.png"
  },
  {
    "code": "003/12",
    "set": "McDonald's Collection 2014 003/12",
    "cost": null,
    "img": "https://images.pokemontcg.io/mcd14/3.png"
  },
  {
    "code": "014/25",
    "set": "McDonald's Collection 2021 014/25",
    "cost": "UnGraded: $0.72",
    "img": "https://images.pokemontcg.io/mcd21/14.png"
  },
  {
    "code": "025/195",
    "set": "Silver Tempest 025/195",
    "cost": "UnGraded: $0.05",
    "img": "https://images.pokemontcg.io/swsh12/25.png"
  }
]