[
  {
    "code": "014/198",
    "set": "Scarlet & Violet 014/198",
    "cost": "UnGraded: $0.12",
    "img": "https://images.pokemontcg.io/sv1/14.png"
  },
  {
    "code": "014/193",
    "set": "Paldea Evolved 014/193",
    "cost": "UnGraded: $0.1",
    "img": "https://images.pokemontcg.io/sv2/14.png"
  },
  {
    "code": "197/193",
    "set": "Paldea Evolved 197/193",
    "cost": "UnGraded: $10.91",
    "img": "https://images.pokemontcg.io/sv2/197.png"
  },
  {
    "code": "077/215",
    "set": "Scarlet & Violet Black Star Promos 077/215",
    "cost": "UnGraded: $1.85",
    "img": "https://images.pokemontcg.io/svp/77.png"
  },
  {
    "code": "017/159",
    "set": "Journey Together 017/159",
    "cost": "UnGraded: $0.04",
    "img": "https://images.pokemontcg.io/sv9/17.png"
  }
]