[
  {
    "set": "Phantom Forces 28/124",
    "cost": "Not PSA Graded: $0.17",
    "img": "https://images.pokemontcg.io/xy4/28.png"
  },
  {
    "set": "Flashfire 36/110",
    "cost": "Not PSA Graded: $0.15",
    "img": "https://images.pokemontcg.io/xy2/36.png"
  },
  {
    "set": "Phantom Forces 29/124",
    "cost": "Not PSA Graded: $0.18",
    "img": "https://images.pokemontcg.io/xy4/29.png"
  },
  {
    "set": "Forbidden Light 37/150",
    "cost": "Not PSA Graded: $0.16",
    "img": "https://images.pokemontcg.io/sm6/37.png"
  },
  {
    "set": "Guardians Rising 43/180",
    "cost": "Not PSA Graded: $0.08",
    "img": "https://images.pokemontcg.io/sm2/43.png"
  },
  {
    "set": "Team Up 49/198",
    "cost": "Not PSA Graded: $0.11",
    "img": "https://images.pokemontcg.io/sm9/49.png"
  },
  {
    "set": "Rebel Clash 63/209",
    "cost": "Not PSA Graded: $0.08",
    "img": "https://images.pokemontcg.io/swsh2/63.png"
  },
  {
    "set": "Cosmic Eclipse 179/272",
    "cost": "Not PSA Graded: $0.11",
    "img": "https://images.pokemontcg.io/sm12/179.png"
  },
  {
    "set": "Fusion Strike 98/284",
    "cost": "Not PSA Graded: $0.07",
    "img": "https://images.pokemontcg.io/swsh8/98.png"
  },
  {
    "set": "Crown Zenith 49/160",
    "cost": "Not PSA Graded: $0.05",
    "img": "https://images.pokemontcg.io/swsh12pt5/49.png"
  },
  {
    "set": "Twilight Masquerade 70/226",
    "cost": "Not PSA Graded: $0.04",
    "img": "https://images.pokemontcg.io/sv6/70.png"
  },
  {
    "set": "Surging Sparks 154/252",
    "cost": "Not PSA Graded: $0.04",
    "img": "https://images.pokemontcg.io/sv8/154.png"
  },
  {
    "set": "Mega Evolution 52/188",
    "cost": "Not PSA Graded: $0.06",
    "img": "https://images.pokemontcg.io/me1/52.png"
  },
  {
    "set": "Mega Evolution 143/188",
    "cost": "Not PSA Graded: $2.46",
    "img": "https://images.pokemontcg.io/me1/143.png"
  }
]