[
  {
    "set": "Dragon Vault 21/21",
    "cost": "Not PSA Graded: $58.11",
    "img": "https://images.pokemontcg.io/dv1/21.png"
  },
  {
    "set": "Fates Collide 21/129",
    "cost": "Not PSA Graded: $0.65",
    "img": "https://images.pokemontcg.io/xy10/21.png"
  },
  {
    "set": "Ancient Origins 25/100",
    "cost": "Not PSA Graded: $4.76",
    "img": "https://images.pokemontcg.io/xy7/25.png"
  },
  {
    "set": "Plasma Blast 30/105",
    "cost": "Not PSA Graded: $12.17",
    "img": "https://images.pokemontcg.io/bw10/30.png"
  },
  {
    "set": "Plasma Freeze 31/122",
    "cost": "Not PSA Graded: $5.03",
    "img": "https://images.pokemontcg.io/bw9/31.png"
  },
  {
    "set": "Next Destinies 38/103",
    "cost": "Not PSA Graded: $8.73",
    "img": "https://images.pokemontcg.io/bw4/38.png"
  },
  {
    "set": "Noble Victories 34/102",
    "cost": "Not PSA Graded: $4.39",
    "img": "https://images.pokemontcg.io/bw3/34.png"
  },
  {
    "set": "Legendary Treasures 43/140",
    "cost": "Not PSA Graded: $1.58",
    "img": "https://images.pokemontcg.io/bw11/43.png"
  },
  {
    "set": "Legendary Treasures 44/140",
    "cost": "Not PSA Graded: $4.87",
    "img": "https://images.pokemontcg.io/bw11/44.png"
  },
  {
    "set": "BW Black Star Promos BW37/101",
    "cost": "Not PSA Graded: $5.58",
    "img": "https://images.pokemontcg.io/bwp/BW37.png"
  },
  {
    "set": "Dragon Majesty 47/80",
    "cost": "Not PSA Graded: $0.58",
    "img": "https://images.pokemontcg.io/sm75/47.png"
  },
  {
    "set": "Dragon Majesty 48/80",
    "cost": "Not PSA Graded: $5.01",
    "img": "https://images.pokemontcg.io/sm75/48.png"
  },
  {
    "set": "BW Black Star Promos BW44/101",
    "cost": "Not PSA Graded: $4.57",
    "img": "https://images.pokemontcg.io/bwp/BW44.png"
  },
  {
    "set": "Cosmic Eclipse 61/272",
    "cost": "Not PSA Graded: $1.18",
    "img": "https://images.pokemontcg.io/sm12/61.png"
  },
  {
    "set": "Unbroken Bonds 50/234",
    "cost": "Not PSA Graded: $0.59",
    "img": "https://images.pokemontcg.io/sm10/50.png"
  },
  {
    "set": "Lost Thunder 63/240",
    "cost": "Not PSA Graded: $1.17",
    "img": "https://images.pokemontcg.io/sm8/63.png"
  },
  {
    "set": "BW Black Star Promos BW58/101",
    "cost": "Not PSA Graded: $18.97",
    "img": "https://images.pokemontcg.io/bwp/BW58.png"
  },
  {
    "set": "BW Black Star Promos BW59/101",
    "cost": "Not PSA Graded: $21.27",
    "img": "https://images.pokemontcg.io/bwp/BW59.png"
  },
  {
    "set": "BW Black Star Promos BW62/101",
    "cost": "Not PSA Graded: $4.55",
    "img": "https://images.pokemontcg.io/bwp/BW62.png"
  },
  {
    "set": "BW Black Star Promos BW63/101",
    "cost": "Not PSA Graded: $5.75",
    "img": "https://images.pokemontcg.io/bwp/BW63.png"
  },
  {
    "set": "Dragon Majesty 74/80",
    "cost": "Not PSA Graded: $56.09",
    "img": "https://images.pokemontcg.io/sm75/74.png"
  },
  {
    "set": "Ancient Origins 86/100",
    "cost": "Not PSA Graded: $38.65",
    "img": "https://images.pokemontcg.io/xy7/86.png"
  },
  {
    "set": "XY Black Star Promos XY80/216",
    "cost": "Not PSA Graded: $45.1",
    "img": "https://images.pokemontcg.io/xyp/XY80.png"
  },
  {
    "set": "XY Black Star Promos XY81/216",
    "cost": "Not PSA Graded: $40.26",
    "img": "https://images.pokemontcg.io/xyp/XY81.png"
  },
  {
    "set": "Next Destinies 96/103",
    "cost": "Not PSA Graded: $274.99",
    "img": "https://images.pokemontcg.io/bw4/96.png"
  },
  {
    "set": "Boundaries Crossed 100/153",
    "cost": "Not PSA Graded: $0.7",
    "img": "https://images.pokemontcg.io/bw7/100.png"
  },
  {
    "set": "Boundaries Crossed 101/153",
    "cost": "Not PSA Graded: $4.17",
    "img": "https://images.pokemontcg.io/bw7/101.png"
  },
  {
    "set": "Legendary Treasures 100/140",
    "cost": "Not PSA Graded: $7.04",
    "img": "https://images.pokemontcg.io/bw11/100.png"
  },
  {
    "set": "Legendary Treasures 101/140",
    "cost": "Not PSA Graded: $5.06",
    "img": "https://images.pokemontcg.io/bw11/101.png"
  },
  {
    "set": "Boundaries Crossed 102/153",
    "cost": "Not PSA Graded: $0.64",
    "img": "https://images.pokemontcg.io/bw7/102.png"
  },
  {
    "set": "Plasma Storm 95/138",
    "cost": "Not PSA Graded: $4.64",
    "img": "https://images.pokemontcg.io/bw8/95.png"
  },
  {
    "set": "Boundaries Crossed 103/153",
    "cost": "Not PSA Graded: $3.31",
    "img": "https://images.pokemontcg.io/bw7/103.png"
  },
  {
    "set": "Plasma Storm 96/138",
    "cost": "Not PSA Graded: $5.23",
    "img": "https://images.pokemontcg.io/bw8/96.png"
  },
  {
    "set": "XY Black Star Promos XY128/216",
    "cost": "Not PSA Graded: $11.67",
    "img": "https://images.pokemontcg.io/xyp/XY128.png"
  },
  {
    "set": "Boundaries Crossed 145/153",
    "cost": "Not PSA Graded: $592.99",
    "img": "https://images.pokemontcg.io/bw7/145.png"
  },
  {
    "set": "SM Black Star Promos SM141/250",
    "cost": "Not PSA Graded: $15.37",
    "img": "https://images.pokemontcg.io/smp/SM141.png"
  },
  {
    "set": "SM Black Star Promos SM142/250",
    "cost": "Not PSA Graded: $1.7",
    "img": "https://images.pokemontcg.io/smp/SM142.png"
  },
  {
    "set": "Boundaries Crossed 146/153",
    "cost": "Not PSA Graded: $370.16",
    "img": "https://images.pokemontcg.io/bw7/146.png"
  },
  {
    "set": "XY Black Star Promos XY160/216",
    "cost": "Not PSA Graded: $2.19",
    "img": "https://images.pokemontcg.io/xyp/XY160.png"
  },
  {
    "set": "Evolving Skies 116/237",
    "cost": "Not PSA Graded: $0.2",
    "img": "https://images.pokemontcg.io/swsh7/116.png"
  },
  {
    "set": "Lost Origin 48/217",
    "cost": "Not PSA Graded: $0.77",
    "img": "https://images.pokemontcg.io/swsh11/48.png"
  },
  {
    "set": "Lost Origin 49/217",
    "cost": "Not PSA Graded: $2.11",
    "img": "https://images.pokemontcg.io/swsh11/49.png"
  },
  {
    "set": "Lost Origin 174/217",
    "cost": "Not PSA Graded: $2.73",
    "img": "https://images.pokemontcg.io/swsh11/174.png"
  },
  {
    "set": "Lost Origin 197/217",
    "cost": "Not PSA Graded: $8.81",
    "img": "https://images.pokemontcg.io/swsh11/197.png"
  },
  {
    "set": "Shrouded Fable 47/99",
    "cost": "Not PSA Graded: $0.09",
    "img": "https://images.pokemontcg.io/sv6pt5/47.png"
  },
  {
    "set": "Surging Sparks 48/252",
    "cost": "Not PSA Graded: $0.58",
    "img": "https://images.pokemontcg.io/sv8/48.png"
  },
  {
    "set": "Surging Sparks 218/252",
    "cost": "Not PSA Graded: $1.84",
    "img": "https://images.pokemontcg.io/sv8/218.png"
  },
  {
    "set": "Black Bolt 28/172",
    "cost": "Not PSA Graded: $2.28",
    "img": "https://images.pokemontcg.io/zsv10pt5/28.png"
  },
  {
    "set": "Black Bolt 157/172",
    "cost": "Not PSA Graded: $1.13",
    "img": "https://images.pokemontcg.io/zsv10pt5/157.png"
  },
  {
    "set": "Black Bolt 165/172",
    "cost": "Not PSA Graded: $71.1",
    "img": "https://images.pokemontcg.io/zsv10pt5/165.png"
  }
]