[
  {
    "set": "Team Rocket Returns 7/111",
    "cost": "Not PSA Graded: $63.31",
    "img": "https://images.pokemontcg.io/ex7/7.png"
  },
  {
    "set": "Delta Species 10/114",
    "cost": "Not PSA Graded: $21.18",
    "img": "https://images.pokemontcg.io/ex11/10.png"
  },
  {
    "set": "FireRed & LeafGreen 7/116",
    "cost": "Not PSA Graded: $25.17",
    "img": "https://images.pokemontcg.io/ex6/7.png"
  },
  {
    "set": "Forbidden Light 12/150",
    "cost": "Not PSA Graded: $0.56",
    "img": "https://images.pokemontcg.io/sm6/12.png"
  },
  {
    "set": "Crimson Invasion 12/126",
    "cost": "Not PSA Graded: $0.77",
    "img": "https://images.pokemontcg.io/sm4/12.png"
  },
  {
    "set": "Fates Collide 37/129",
    "cost": "Not PSA Graded: $0.38",
    "img": "https://images.pokemontcg.io/xy10/37.png"
  },
  {
    "set": "HS—Triumphant 44/103",
    "cost": "Not PSA Graded: $0.53",
    "img": "https://images.pokemontcg.io/hgss4/44.png"
  },
  {
    "set": "Jungle 39/64",
    "cost": null,
    "img": "https://images.pokemontcg.io/base2/39.png"
  },
  {
    "set": "Base Set 2 52/130",
    "cost": "Not PSA Graded: $1.69",
    "img": "https://images.pokemontcg.io/base4/52.png"
  },
  {
    "set": "Team Up 64/198",
    "cost": "Not PSA Graded: $0.88",
    "img": "https://images.pokemontcg.io/sm9/64.png"
  },
  {
    "set": "Dragons Exalted 61/128",
    "cost": "Not PSA Graded: $0.45",
    "img": "https://images.pokemontcg.io/bw6/61.png"
  },
  {
    "set": "Legends Awakened 63/146",
    "cost": "Not PSA Graded: $0.43",
    "img": "https://images.pokemontcg.io/dp6/63.png"
  },
  {
    "set": "Unified Minds 75/260",
    "cost": "Not PSA Graded: $0.47",
    "img": "https://images.pokemontcg.io/sm11/75.png"
  },
  {
    "set": "Aquapolis 54/182",
    "cost": "Not PSA Graded: $5.03",
    "img": "https://images.pokemontcg.io/ecard2/54.png"
  },
  {
    "set": "BREAKthrough 78/165",
    "cost": "Not PSA Graded: $0.46",
    "img": "https://images.pokemontcg.io/xy8/78.png"
  },
  {
    "set": "BREAKthrough 79/165",
    "cost": "Not PSA Graded: $3.9",
    "img": "https://images.pokemontcg.io/xy8/79.png"
  },
  {
    "set": "Unbroken Bonds 91/234",
    "cost": "Not PSA Graded: $0.39",
    "img": "https://images.pokemontcg.io/sm10/91.png"
  },
  {
    "set": "SM Black Star Promos SM187/250",
    "cost": "Not PSA Graded: $14.28",
    "img": "https://images.pokemontcg.io/smp/SM187.png"
  },
  {
    "set": "Battle Styles 70/183",
    "cost": "Not PSA Graded: $0.14",
    "img": "https://images.pokemontcg.io/swsh5/70.png"
  },
  {
    "set": "151 105/207",
    "cost": "Not PSA Graded: $0.17",
    "img": "https://images.pokemontcg.io/sv3pt5/105.png"
  },
  {
    "set": "Stellar Crown 73/175",
    "cost": "Not PSA Graded: $0.07",
    "img": "https://images.pokemontcg.io/sv7/73.png"
  },
  {
    "set": "Journey Together 57/190",
    "cost": "Not PSA Graded: $0.05",
    "img": "https://images.pokemontcg.io/sv9/57.png"
  }
]