[
  {
    "set": "Southern Islands 1/18",
    "cost": null,
    "img": "https://images.pokemontcg.io/si1/1.png"
  },
  {
    "set": "POP Series 4 4/17",
    "cost": "Not PSA Graded: $58.32",
    "img": "https://images.pokemontcg.io/pop4/4.png"
  },
  {
    "set": "POP Series 5 3/17",
    "cost": "Not PSA Graded: $248",
    "img": "https://images.pokemontcg.io/pop5/3.png"
  },
  {
    "set": "Legend Maker 10/93",
    "cost": "Not PSA Graded: $124.29",
    "img": "https://images.pokemontcg.io/ex12/10.png"
  },
  {
    "set": "Wizards Black Star Promos 8/53",
    "cost": "Not PSA Graded: $7.74",
    "img": "https://images.pokemontcg.io/basep/8.png"
  },
  {
    "set": "Pokémon Rumble 10/16",
    "cost": "Not PSA Graded: $246.91",
    "img": "https://images.pokemontcg.io/ru1/10.png"
  },
  {
    "set": "Wizards Black Star Promos 9/53",
    "cost": "Not PSA Graded: $60.43",
    "img": "https://images.pokemontcg.io/basep/9.png"
  },
  {
    "set": "Secret Wonders 15/132",
    "cost": "Not PSA Graded: $110.5",
    "img": "https://images.pokemontcg.io/dp3/15.png"
  },
  {
    "set": "Expedition Base Set 19/165",
    "cost": "Not PSA Graded: $197.97",
    "img": "https://images.pokemontcg.io/ecard1/19.png"
  },
  {
    "set": "Fates Collide 29/129",
    "cost": "Not PSA Graded: $6.53",
    "img": "https://images.pokemontcg.io/xy10/29.png"
  },
  {
    "set": "Hidden Fates 32/69",
    "cost": "Not PSA Graded: $1.52",
    "img": "https://images.pokemontcg.io/sm115/32.png"
  },
  {
    "set": "Dragons Exalted 46/128",
    "cost": "Not PSA Graded: $84.19",
    "img": "https://images.pokemontcg.io/bw6/46.png"
  },
  {
    "set": "Nintendo Black Star Promos 40/40",
    "cost": "Not PSA Graded: $80.04",
    "img": "https://images.pokemontcg.io/np/40.png"
  },
  {
    "set": "Shining Legends 40/81",
    "cost": "Not PSA Graded: $83.07",
    "img": "https://images.pokemontcg.io/sm35/40.png"
  },
  {
    "set": "Wizards Black Star Promos 47/53",
    "cost": "Not PSA Graded: $97.79",
    "img": "https://images.pokemontcg.io/basep/47.png"
  },
  {
    "set": "Evolutions 53/113",
    "cost": "Not PSA Graded: $14.51",
    "img": "https://images.pokemontcg.io/xy12/53.png"
  },
  {
    "set": "Expedition Base Set 55/165",
    "cost": "Not PSA Graded: $63.78",
    "img": "https://images.pokemontcg.io/ecard1/55.png"
  },
  {
    "set": "Darkness Ablaze 69/201",
    "cost": "Not PSA Graded: $2.73",
    "img": "https://images.pokemontcg.io/swsh3/69.png"
  },
  {
    "set": "Unified Minds 71/260",
    "cost": "Not PSA Graded: $88.25",
    "img": "https://images.pokemontcg.io/sm11/71.png"
  },
  {
    "set": "Legend Maker 88/93",
    "cost": "Not PSA Graded: $274.54",
    "img": "https://images.pokemontcg.io/ex12/88.png"
  },
  {
    "set": "Unbroken Bonds 76/234",
    "cost": "Not PSA Graded: $8.83",
    "img": "https://images.pokemontcg.io/sm10/76.png"
  },
  {
    "set": "HS—Triumphant 97/103",
    "cost": "Not PSA Graded: $149.99",
    "img": "https://images.pokemontcg.io/hgss4/97.png"
  },
  {
    "set": "Holon Phantoms 100/111",
    "cost": "Not PSA Graded: $240",
    "img": "https://images.pokemontcg.io/ex13/100.png"
  },
  {
    "set": "BW Black Star Promos BW98/101",
    "cost": "Not PSA Graded: $100",
    "img": "https://images.pokemontcg.io/bwp/BW98.png"
  },
  {
    "set": "Holon Phantoms 111/111",
    "cost": "Not PSA Graded: $173.98",
    "img": "https://images.pokemontcg.io/ex13/111.png"
  },
  {
    "set": "Dragon Frontiers 101/101",
    "cost": "Not PSA Graded: $1700",
    "img": "https://images.pokemontcg.io/ex15/101.png"
  },
  {
    "set": "XY Black Star Promos XY110/216",
    "cost": "Not PSA Graded: $118.18",
    "img": "https://images.pokemontcg.io/xyp/XY110.png"
  },
  {
    "set": "Dragons Exalted 120/128",
    "cost": "Not PSA Graded: $534.65",
    "img": "https://images.pokemontcg.io/bw6/120.png"
  },
  {
    "set": "XY Black Star Promos XY126/216",
    "cost": "Not PSA Graded: $122.79",
    "img": "https://images.pokemontcg.io/xyp/XY126.png"
  },
  {
    "set": "Legendary Treasures RC24/140",
    "cost": "Not PSA Graded: $200.34",
    "img": "https://images.pokemontcg.io/bw11/RC24.png"
  },
  {
    "set": "SM Black Star Promos SM191/250",
    "cost": "Not PSA Graded: $239.87",
    "img": "https://images.pokemontcg.io/smp/SM191.png"
  },
  {
    "set": "XY Black Star Promos XY192/216",
    "cost": "Not PSA Graded: $55.7",
    "img": "https://images.pokemontcg.io/xyp/XY192.png"
  },
  {
    "set": "SM Black Star Promos SM215/250",
    "cost": "Not PSA Graded: $16.28",
    "img": "https://images.pokemontcg.io/smp/SM215.png"
  },
  {
    "set": "Unified Minds 222/260",
    "cost": "Not PSA Graded: $139.77",
    "img": "https://images.pokemontcg.io/sm11/222.png"
  },
  {
    "set": "Unified Minds 242/260",
    "cost": "Not PSA Graded: $332.33",
    "img": "https://images.pokemontcg.io/sm11/242.png"
  },
  {
    "set": "Celebrations 11/25",
    "cost": "Not PSA Graded: $2.53",
    "img": "https://images.pokemontcg.io/cel25/11.png"
  },
  {
    "set": "Celebrations 25/25",
    "cost": "Not PSA Graded: $43.75",
    "img": "https://images.pokemontcg.io/cel25/25.png"
  },
  {
    "set": "Celebrations: Classic Collection 88/25",
    "cost": "Not PSA Graded: $11.84",
    "img": "https://images.pokemontcg.io/cel25c/88_A.png"
  },
  {
    "set": "Fusion Strike 113/284",
    "cost": "Not PSA Graded: $2.19",
    "img": "https://images.pokemontcg.io/swsh8/113.png"
  },
  {
    "set": "Fusion Strike 114/284",
    "cost": "Not PSA Graded: $9.65",
    "img": "https://images.pokemontcg.io/swsh8/114.png"
  },
  {
    "set": "Fusion Strike 250/284",
    "cost": "Not PSA Graded: $27.36",
    "img": "https://images.pokemontcg.io/swsh8/250.png"
  },
  {
    "set": "Fusion Strike 251/284",
    "cost": "Not PSA Graded: $94.56",
    "img": "https://images.pokemontcg.io/swsh8/251.png"
  },
  {
    "set": "Fusion Strike 268/284",
    "cost": "Not PSA Graded: $57.95",
    "img": "https://images.pokemontcg.io/swsh8/268.png"
  },
  {
    "set": "Fusion Strike 269/284",
    "cost": "Not PSA Graded: $207.7",
    "img": "https://images.pokemontcg.io/swsh8/269.png"
  },
  {
    "set": "Lost Origin Trainer Gallery TG30/30",
    "cost": "Not PSA Graded: $18.15",
    "img": "https://images.pokemontcg.io/swsh11tg/TG30.png"
  },
  {
    "set": "Crown Zenith 60/160",
    "cost": "Not PSA Graded: $2.4",
    "img": "https://images.pokemontcg.io/swsh12pt5/60.png"
  },
  {
    "set": "Crown Zenith Galarian Gallery GG10/70",
    "cost": "Not PSA Graded: $31.69",
    "img": "https://images.pokemontcg.io/swsh12pt5gg/GG10.png"
  },
  {
    "set": "151 151/207",
    "cost": "Not PSA Graded: $9.51",
    "img": "https://images.pokemontcg.io/sv3pt5/151.png"
  },
  {
    "set": "151 193/207",
    "cost": "Not PSA Graded: $22.35",
    "img": "https://images.pokemontcg.io/sv3pt5/193.png"
  },
  {
    "set": "151 205/207",
    "cost": "Not PSA Graded: $16.78",
    "img": "https://images.pokemontcg.io/sv3pt5/205.png"
  },
  {
    "set": "Scarlet & Violet Black Star Promos 53/196",
    "cost": "Not PSA Graded: $49.98",
    "img": "https://images.pokemontcg.io/svp/53.png"
  },
  {
    "set": "Paldean Fates 232/245",
    "cost": "Not PSA Graded: $515.61",
    "img": "https://images.pokemontcg.io/sv4pt5/232.png"
  },
  {
    "set": "Paldean Fates 216/245",
    "cost": "Not PSA Graded: $23.78",
    "img": "https://images.pokemontcg.io/sv4pt5/216.png"
  }
]