[
  {
    "set": "McDonald's Collection 2012 9/12",
    "cost": "Not PSA Graded: $12.89",
    "img": "https://images.pokemontcg.io/mcd12/9.png"
  },
  {
    "set": "Champion's Path 39/80",
    "cost": "Not PSA Graded: $0.09",
    "img": "https://images.pokemontcg.io/swsh35/39.png"
  },
  {
    "set": "Shining Legends 48/81",
    "cost": "Not PSA Graded: $0.14",
    "img": "https://images.pokemontcg.io/sm35/48.png"
  },
  {
    "set": "Phantom Forces 56/124",
    "cost": "Not PSA Graded: $0.16",
    "img": "https://images.pokemontcg.io/xy4/56.png"
  },
  {
    "set": "Black & White 66/115",
    "cost": "Not PSA Graded: $0.2",
    "img": "https://images.pokemontcg.io/bw1/66.png"
  },
  {
    "set": "Emerging Powers 64/98",
    "cost": "Not PSA Graded: $0.27",
    "img": "https://images.pokemontcg.io/bw2/64.png"
  },
  {
    "set": "Plasma Storm 82/138",
    "cost": "Not PSA Graded: $0.26",
    "img": "https://images.pokemontcg.io/bw8/82.png"
  },
  {
    "set": "Plasma Storm 83/138",
    "cost": "Not PSA Graded: $0.25",
    "img": "https://images.pokemontcg.io/bw8/83.png"
  },
  {
    "set": "Boundaries Crossed 90/153",
    "cost": "Not PSA Graded: $0.24",
    "img": "https://images.pokemontcg.io/bw7/90.png"
  },
  {
    "set": "Darkness Ablaze 106/201",
    "cost": "Not PSA Graded: $0.13",
    "img": "https://images.pokemontcg.io/swsh3/106.png"
  },
  {
    "set": "Legendary Treasures RC13/140",
    "cost": "Not PSA Graded: $4.93",
    "img": "https://images.pokemontcg.io/bw11/RC13.png"
  },
  {
    "set": "Unified Minds 135/260",
    "cost": "Not PSA Graded: $0.16",
    "img": "https://images.pokemontcg.io/sm11/135.png"
  },
  {
    "set": "Brilliant Stars 90/186",
    "cost": "Not PSA Graded: $0.1",
    "img": "https://images.pokemontcg.io/swsh9/90.png"
  },
  {
    "set": "Crown Zenith 77/160",
    "cost": "Not PSA Graded: $0.08",
    "img": "https://images.pokemontcg.io/swsh12pt5/77.png"
  },
  {
    "set": "Paradox Rift 114/266",
    "cost": "Not PSA Graded: $0.04",
    "img": "https://images.pokemontcg.io/sv4/114.png"
  },
  {
    "set": "Journey Together 96/190",
    "cost": "Not PSA Graded: $0.06",
    "img": "https://images.pokemontcg.io/sv9/96.png"
  },
  {
    "set": "Destined Rivals 130/244",
    "cost": "Not PSA Graded: $0.05",
    "img": "https://images.pokemontcg.io/sv10/130.png"
  },
  {
    "set": "White Flare 55/173",
    "cost": "Not PSA Graded: $0.09",
    "img": "https://images.pokemontcg.io/rsv10pt5/55.png"
  },
  {
    "set": "White Flare 136/173",
    "cost": "Not PSA Graded: $11.28",
    "img": "https://images.pokemontcg.io/rsv10pt5/136.png"
  }
]