[
  {
    "code": "010/105",
    "set": "Neo Destiny 010/105",
    "cost": null,
    "img": "https://images.pokemontcg.io/neo4/10.png"
  },
  {
    "code": "017/115",
    "set": "Unseen Forces 017/115",
    "cost": "UnGraded: $81.65",
    "img": "https://images.pokemontcg.io/ex10/17.png"
  },
  {
    "code": "HGSS09/25",
    "set": "HGSS Black Star Promos HGSS09/25",
    "cost": "UnGraded: $36.02",
    "img": "https://images.pokemontcg.io/hsp/HGSS09.png"
  },
  {
    "code": "012/101",
    "set": "Dragon Frontiers 012/101",
    "cost": "UnGraded: $49.07",
    "img": "https://images.pokemontcg.io/ex15/12.png"
  },
  {
    "code": "016/123",
    "set": "Mysterious Treasures 016/123",
    "cost": "UnGraded: $20.69",
    "img": "https://images.pokemontcg.io/dp2/16.png"
  },
  {
    "code": "017/111",
    "set": "Neo Genesis 017/111",
    "cost": null,
    "img": "https://images.pokemontcg.io/neo1/17.png"
  },
  {
    "code": "018/111",
    "set": "Neo Genesis 018/111",
    "cost": null,
    "img": "https://images.pokemontcg.io/neo1/18.png"
  },
  {
    "code": "020/162",
    "set": "BREAKthrough 020/162",
    "cost": "UnGraded: $4.55",
    "img": "https://images.pokemontcg.io/xy8/20.png"
  },
  {
    "code": "032/123",
    "set": "HeartGold & SoulSilver 032/123",
    "cost": "UnGraded: $7.43",
    "img": "https://images.pokemontcg.io/hgss1/32.png"
  },
  {
    "code": "035/95",
    "set": "Call of Legends 035/95",
    "cost": "UnGraded: $4.33",
    "img": "https://images.pokemontcg.io/col1/35.png"
  },
  {
    "code": "028/165",
    "set": "Expedition Base Set 028/165",
    "cost": "UnGraded: $165",
    "img": "https://images.pokemontcg.io/ecard1/28.png"
  },
  {
    "code": "034/40",
    "set": "Nintendo Black Star Promos 034/40",
    "cost": "UnGraded: $24.9",
    "img": "https://images.pokemontcg.io/np/34.png"
  },
  {
    "code": "042/214",
    "set": "Lost Thunder 042/214",
    "cost": "UnGraded: $10.13",
    "img": "https://images.pokemontcg.io/sm8/42.png"
  },
  {
    "code": "064/165",
    "set": "Expedition Base Set 064/165",
    "cost": "UnGraded: $44.42",
    "img": "https://images.pokemontcg.io/ecard1/64.png"
  },
  {
    "code": "065/165",
    "set": "Expedition Base Set 065/165",
    "cost": "UnGraded: $20.45",
    "img": "https://images.pokemontcg.io/ecard1/65.png"
  },
  {
    "code": "110/123",
    "set": "HeartGold & SoulSilver 110/123",
    "cost": "UnGraded: $44.9",
    "img": "https://images.pokemontcg.io/hgss1/110.png"
  },
  {
    "code": "099/100",
    "set": "Sandstorm 099/100",
    "cost": "UnGraded: $142.47",
    "img": "https://images.pokemontcg.io/ex2/99.png"
  },
  {
    "code": "110/115",
    "set": "Unseen Forces 110/115",
    "cost": "UnGraded: $133.46",
    "img": "https://images.pokemontcg.io/ex10/110.png"
  },
  {
    "code": "SM185/248",
    "set": "SM Black Star Promos SM185/248",
    "cost": "UnGraded: $4.4",
    "img": "https://images.pokemontcg.io/smp/SM185.png"
  },
  {
    "code": "052/189",
    "set": "Astral Radiance 052/189",
    "cost": "UnGraded: $0.39",
    "img": "https://images.pokemontcg.io/swsh10/52.png"
  },
  {
    "code": "053/189",
    "set": "Astral Radiance 053/189",
    "cost": "UnGraded: $1.33",
    "img": "https://images.pokemontcg.io/swsh10/53.png"
  },
  {
    "code": "054/189",
    "set": "Astral Radiance 054/189",
    "cost": "UnGraded: $1.94",
    "img": "https://images.pokemontcg.io/swsh10/54.png"
  },
  {
    "code": "169/189",
    "set": "Astral Radiance 169/189",
    "cost": "UnGraded: $4.25",
    "img": "https://images.pokemontcg.io/swsh10/169.png"
  },
  {
    "code": "193/189",
    "set": "Astral Radiance 193/189",
    "cost": "UnGraded: $11.13",
    "img": "https://images.pokemontcg.io/swsh10/193.png"
  },
  {
    "code": "SWSH237/307",
    "set": "SWSH Black Star Promos SWSH237/307",
    "cost": "UnGraded: $0.99",
    "img": "https://images.pokemontcg.io/swshp/SWSH237.png"
  },
  {
    "code": "034/182",
    "set": "Destined Rivals 034/182",
    "cost": "UnGraded: $0.28",
    "img": "https://images.pokemontcg.io/sv10/34.png"
  },
  {
    "code": "190/182",
    "set": "Destined Rivals 190/182",
    "cost": "UnGraded: $25.42",
    "img": "https://images.pokemontcg.io/sv10/190.png"
  }
]