[
  {
    "set": "Battle Styles 85/183",
    "cost": "Not PSA Graded: $0.69",
    "img": "https://images.pokemontcg.io/swsh5/85.png"
  },
  {
    "set": "Battle Styles 86/183",
    "cost": "Not PSA Graded: $1.59",
    "img": "https://images.pokemontcg.io/swsh5/86.png"
  },
  {
    "set": "Battle Styles 87/183",
    "cost": "Not PSA Graded: $0.7",
    "img": "https://images.pokemontcg.io/swsh5/87.png"
  },
  {
    "set": "Battle Styles 88/183",
    "cost": "Not PSA Graded: $1.43",
    "img": "https://images.pokemontcg.io/swsh5/88.png"
  },
  {
    "set": "Battle Styles 150/183",
    "cost": "Not PSA Graded: $3.46",
    "img": "https://images.pokemontcg.io/swsh5/150.png"
  },
  {
    "set": "Battle Styles 151/183",
    "cost": "Not PSA Graded: $15.91",
    "img": "https://images.pokemontcg.io/swsh5/151.png"
  },
  {
    "set": "Battle Styles 152/183",
    "cost": "Not PSA Graded: $3.35",
    "img": "https://images.pokemontcg.io/swsh5/152.png"
  },
  {
    "set": "Battle Styles 153/183",
    "cost": "Not PSA Graded: $15.63",
    "img": "https://images.pokemontcg.io/swsh5/153.png"
  },
  {
    "set": "Battle Styles 168/183",
    "cost": "Not PSA Graded: $34.08",
    "img": "https://images.pokemontcg.io/swsh5/168.png"
  },
  {
    "set": "Battle Styles 170/183",
    "cost": "Not PSA Graded: $77.21",
    "img": "https://images.pokemontcg.io/swsh5/170.png"
  },
  {
    "set": "SWSH Black Star Promos SWSH106/304",
    "cost": "Not PSA Graded: $0.9",
    "img": "https://images.pokemontcg.io/swshp/SWSH106.png"
  },
  {
    "set": "SWSH Black Star Promos SWSH107/304",
    "cost": "Not PSA Graded: $0.95",
    "img": "https://images.pokemontcg.io/swshp/SWSH107.png"
  },
  {
    "set": "Battle Styles 167/183",
    "cost": "Not PSA Graded: $9.53",
    "img": "https://images.pokemontcg.io/swsh5/167.png"
  },
  {
    "set": "Battle Styles 169/183",
    "cost": "Not PSA Graded: $8.27",
    "img": "https://images.pokemontcg.io/swsh5/169.png"
  },
  {
    "set": "Chilling Reign 44/233",
    "cost": "Not PSA Graded: $0.28",
    "img": "https://images.pokemontcg.io/swsh6/44.png"
  },
  {
    "set": "Chilling Reign 108/233",
    "cost": "Not PSA Graded: $0.31",
    "img": "https://images.pokemontcg.io/swsh6/108.png"
  },
  {
    "set": "Brilliant Stars Trainer Gallery TG18/30",
    "cost": "Not PSA Graded: $3.99",
    "img": "https://images.pokemontcg.io/swsh9tg/TG18.png"
  },
  {
    "set": "Brilliant Stars Trainer Gallery TG19/30",
    "cost": "Not PSA Graded: $6.69",
    "img": "https://images.pokemontcg.io/swsh9tg/TG19.png"
  },
  {
    "set": "Brilliant Stars Trainer Gallery TG20/30",
    "cost": "Not PSA Graded: $4.94",
    "img": "https://images.pokemontcg.io/swsh9tg/TG20.png"
  },
  {
    "set": "Brilliant Stars Trainer Gallery TG21/30",
    "cost": "Not PSA Graded: $8.72",
    "img": "https://images.pokemontcg.io/swsh9tg/TG21.png"
  },
  {
    "set": "Brilliant Stars Trainer Gallery TG29/30",
    "cost": "Not PSA Graded: $3.45",
    "img": "https://images.pokemontcg.io/swsh9tg/TG29.png"
  },
  {
    "set": "Brilliant Stars Trainer Gallery TG30/30",
    "cost": "Not PSA Graded: $3.55",
    "img": "https://images.pokemontcg.io/swsh9tg/TG30.png"
  }
]